prophecy_lineage_extractor/__init__.py
prophecy_lineage_extractor/__main__.py
prophecy_lineage_extractor/constants.py
prophecy_lineage_extractor/messages.py
prophecy_lineage_extractor/reader/__init__.py
prophecy_lineage_extractor/reader/base_reader.py
prophecy_lineage_extractor/reader/graphql.py
prophecy_lineage_extractor/reader/rest_reader.py
prophecy_lineage_extractor/reader/rest_req.py
prophecy_lineage_extractor/reader/websocket_reader.py
prophecy_lineage_extractor/utils.py
prophecy_lineage_extractor/writer/__init__.py
prophecy_lineage_extractor/writer/base_writer.py
prophecy_lineage_extractor/writer/openlineage_writer.py
prophecy_lineage_extractor/writer/xlxs_writer.py
prophecy_lineage_extractor-0.21.1.dist-info/METADATA
prophecy_lineage_extractor-0.21.1.dist-info/WHEEL
prophecy_lineage_extractor-0.21.1.dist-info/entry_points.txt
prophecy_lineage_extractor-0.21.1.dist-info/RECORD
