Metadata-Version: 2.3
Name: prophecy-lineage-extractor
Version: 0.21.1
Summary: 
Author: Ashish Patel
Author-email: ashishpatel0720@gmail.com
Requires-Python: >=3.9,<4.0
Classifier: Programming Language :: Python :: 3
Classifier: Programming Language :: Python :: 3.9
Classifier: Programming Language :: Python :: 3.10
Classifier: Programming Language :: Python :: 3.11
Classifier: Programming Language :: Python :: 3.12
Classifier: Programming Language :: Python :: 3.13
Requires-Dist: openpyxl (>=3.1.5,<4.0.0)
Requires-Dist: pandas (>=2.2.3,<3.0.0)
Requires-Dist: requests (>=2.32.3,<3.0.0)
Requires-Dist: sqlglot (>=18.11.6,<19.0.0)
Requires-Dist: websocket-client (>=1.8.0,<2.0.0)
